[
  {
    "author": "ZanarkTempest",
    "link_thumb": "https://live.staticflickr.com/65535/51786501257_84f9d862f8_o.gif",
    "link_bin": "https://github.com/lmbstudiocontact/mb6_1/raw/main/1821.bin",
    "id_bin": "1821",
    "list_language": [],
    "array_tags": [
      "sonic",
      "cartoon"
    ],
    "list_album": [
      {
        "id_album": "-2075887794",
        "link_thumb": "https://live.staticflickr.com/65535/51786501257_84f9d862f8_o.gif",
        "title": "Cartoon"
      }
    ]
  },
  {
    "author": "ZanarkTempest",
    "link_thumb": "https://live.staticflickr.com/65535/51787940569_e4bc69f21b_o.gif",
    "link_bin": "https://github.com/lmbstudiocontact/mb6_1/raw/main/1881.bin",
    "id_bin": "1881",
    "list_language": [],
    "array_tags": [
      "marvel"
    ],
    "list_album": [
      {
        "id_album": "-2075887794",
        "link_thumb": "https://live.staticflickr.com/65535/51787940569_e4bc69f21b_o.gif",
        "title": "Cartoon"
      }
    ]
  },
  {
    "author": "ZanarkTempest",
    "link_thumb": "https://live.staticflickr.com/65535/51787940509_217a00893f_o.gif",
    "link_bin": "https://github.com/lmbstudiocontact/mb6_1/raw/main/1882.bin",
    "id_bin": "1882",
    "list_language": [],
    "array_tags": [
      "marvel"
    ],
    "list_album": [
      {
        "id_album": "-2075887794",
        "link_thumb": "https://live.staticflickr.com/65535/51787940509_217a00893f_o.gif",
        "title": "Cartoon"
      }
    ]
  },
  {
    "author": "ZanarkTempest",
    "link_thumb": "https://live.staticflickr.com/65535/51787316941_5bf68dab03_o.gif",
    "link_bin": "https://github.com/lmbstudiocontact/mb6_1/raw/main/1883.bin",
    "id_bin": "1883",
    "list_language": [],
    "array_tags": [
      "marvel"
    ],
    "list_album": [
      {
        "id_album": "-2075887794",
        "link_thumb": "https://live.staticflickr.com/65535/51787316941_5bf68dab03_o.gif",
        "title": "Cartoon"
      }
    ]
  },
  {
    "author": "ZanarkTempest",
    "link_thumb": "https://live.staticflickr.com/65535/51787316851_86504bc644_o.gif",
    "link_bin": "https://github.com/lmbstudiocontact/mb6_1/raw/main/1884.bin",
    "id_bin": "1884",
    "list_language": [],
    "array_tags": [
      "marvel"
    ],
    "list_album": [
      {
        "id_album": "-2075887794",
        "link_thumb": "https://live.staticflickr.com/65535/51787316851_86504bc644_o.gif",
        "title": "Cartoon"
      }
    ]
  },
  {
    "author": "ZanarkTempest",
    "link_thumb": "https://live.staticflickr.com/65535/51787940334_31ff066b04_o.gif",
    "link_bin": "https://github.com/lmbstudiocontact/mb6_1/raw/main/1885.bin",
    "id_bin": "1885",
    "list_language": [],
    "array_tags": [
      "marvel"
    ],
    "list_album": [
      {
        "id_album": "-2075887794",
        "link_thumb": "https://live.staticflickr.com/65535/51787940334_31ff066b04_o.gif",
        "title": "Cartoon"
      }
    ]
  },
  {
    "author": "ZanarkTempest",
    "link_thumb": "https://live.staticflickr.com/65535/51787316716_388efc2652_o.gif",
    "link_bin": "https://github.com/lmbstudiocontact/mb6_1/raw/main/1886.bin",
    "id_bin": "1886",
    "list_language": [],
    "array_tags": [
      "marvel"
    ],
    "list_album": [
      {
        "id_album": "-2075887794",
        "link_thumb": "https://live.staticflickr.com/65535/51787316716_388efc2652_o.gif",
        "title": "Cartoon"
      }
    ]
  },
  {
    "author": "ZanarkTempest",
    "link_thumb": "https://live.staticflickr.com/65535/51787940229_9b1b15c186_o.gif",
    "link_bin": "https://github.com/lmbstudiocontact/mb6_1/raw/main/1887.bin",
    "id_bin": "1887",
    "list_language": [],
    "array_tags": [
      "marvel"
    ],
    "list_album": [
      {
        "id_album": "-2075887794",
        "link_thumb": "https://live.staticflickr.com/65535/51787940229_9b1b15c186_o.gif",
        "title": "Cartoon"
      }
    ]
  },
  {
    "author": "ZanarkTempest",
    "link_thumb": "https://live.staticflickr.com/65535/51788188560_772335a71d_o.gif",
    "link_bin": "https://github.com/lmbstudiocontact/mb6_1/raw/main/1888.bin",
    "id_bin": "1888",
    "list_language": [],
    "array_tags": [
      "marvel"
    ],
    "list_album": [
      {
        "id_album": "-2075887794",
        "link_thumb": "https://live.staticflickr.com/65535/51788188560_772335a71d_o.gif",
        "title": "Cartoon"
      }
    ]
  },
  {
    "author": "ZanarkTempest",
    "link_thumb": "https://live.staticflickr.com/65535/51788188465_73ea8ff541_o.gif",
    "link_bin": "https://github.com/lmbstudiocontact/mb6_1/raw/main/1889.bin",
    "id_bin": "1889",
    "list_language": [],
    "array_tags": [
      "marvel"
    ],
    "list_album": [
      {
        "id_album": "-2075887794",
        "link_thumb": "https://live.staticflickr.com/65535/51788188465_73ea8ff541_o.gif",
        "title": "Cartoon"
      }
    ]
  },
  {
    "author": "ZanarkTempest",
    "link_thumb": "https://live.staticflickr.com/65535/51788188180_98675cf817_o.gif",
    "link_bin": "https://github.com/lmbstudiocontact/mb6_1/raw/main/1901.bin",
    "id_bin": "1901",
    "list_language": [],
    "array_tags": [
      "warnerbros",
      "cartoon",
      "looneytunes"
    ],
    "list_album": [
      {
        "id_album": "-2075887794",
        "link_thumb": "https://live.staticflickr.com/65535/51788188180_98675cf817_o.gif",
        "title": "Cartoon"
      }
    ]
  },
  {
    "author": "ZanarkTempest",
    "link_thumb": "https://live.staticflickr.com/65535/51787565208_533e1cceae_o.gif",
    "link_bin": "https://github.com/lmbstudiocontact/mb6_1/raw/main/1902.bin",
    "id_bin": "1902",
    "list_language": [],
    "array_tags": [
      "warnerbros",
      "cartoon",
      "looneytunes"
    ],
    "list_album": [
      {
        "id_album": "-2075887794",
        "link_thumb": "https://live.staticflickr.com/65535/51787565208_533e1cceae_o.gif",
        "title": "Cartoon"
      }
    ]
  },
  {
    "author": "ZanarkTempest",
    "link_thumb": "https://live.staticflickr.com/65535/51787315971_d17775dff5_o.gif",
    "link_bin": "https://github.com/lmbstudiocontact/mb6_1/raw/main/1903.bin",
    "id_bin": "1903",
    "list_language": [],
    "array_tags": [
      "warnerbros",
      "cartoon",
      "looneytunes"
    ],
    "list_album": [
      {
        "id_album": "-2075887794",
        "link_thumb": "https://live.staticflickr.com/65535/51787315971_d17775dff5_o.gif",
        "title": "Cartoon"
      }
    ]
  },
  {
    "author": "ZanarkTempest",
    "link_thumb": "https://live.staticflickr.com/65535/51787939579_b0501c4322_o.gif",
    "link_bin": "https://github.com/lmbstudiocontact/mb6_1/raw/main/1904.bin",
    "id_bin": "1904",
    "list_language": [],
    "array_tags": [
      "warnerbros",
      "cartoon",
      "looneytunes"
    ],
    "list_album": [
      {
        "id_album": "-2075887794",
        "link_thumb": "https://live.staticflickr.com/65535/51787939579_b0501c4322_o.gif",
        "title": "Cartoon"
      }
    ]
  },
  {
    "author": "ZanarkTempest",
    "link_thumb": "https://live.staticflickr.com/65535/51788187890_bac8287163_o.gif",
    "link_bin": "https://github.com/lmbstudiocontact/mb6_1/raw/main/1905.bin",
    "id_bin": "1905",
    "list_language": [],
    "array_tags": [
      "cartoon"
    ],
    "list_album": [
      {
        "id_album": "-2075887794",
        "link_thumb": "https://live.staticflickr.com/65535/51788187890_bac8287163_o.gif",
        "title": "Cartoon"
      }
    ]
  },
  {
    "author": "ZanarkTempest",
    "link_thumb": "https://live.staticflickr.com/65535/51786497757_e096b0c95c_o.gif",
    "link_bin": "https://github.com/lmbstudiocontact/mb6_1/raw/main/1906.bin",
    "id_bin": "1906",
    "list_language": [],
    "array_tags": [
      "warnerbros",
      "cartoon",
      "looneytunes"
    ],
    "list_album": [
      {
        "id_album": "-2075887794",
        "link_thumb": "https://live.staticflickr.com/65535/51786497757_e096b0c95c_o.gif",
        "title": "Cartoon"
      }
    ]
  },
  {
    "author": "ZanarkTempest",
    "link_thumb": "https://live.staticflickr.com/65535/51787939394_3a90f3697a_o.gif",
    "link_bin": "https://github.com/lmbstudiocontact/mb6_1/raw/main/1907.bin",
    "id_bin": "1907",
    "list_language": [],
    "array_tags": [
      "cartoon",
      "looneytunes"
    ],
    "list_album": [
      {
        "id_album": "-2075887794",
        "link_thumb": "https://live.staticflickr.com/65535/51787939394_3a90f3697a_o.gif",
        "title": "Cartoon"
      }
    ]
  },
  {
    "author": "ZanarkTempest",
    "link_thumb": "https://live.staticflickr.com/65535/51788187135_3cf8c03f70_o.gif",
    "link_bin": "https://github.com/lmbstudiocontact/mb6_1/raw/main/1917.bin",
    "id_bin": "1917",
    "list_language": [],
    "array_tags": [
      "sonic",
      "cartoon",
      "games"
    ],
    "list_album": [
      {
        "id_album": "-2075887794",
        "link_thumb": "https://live.staticflickr.com/65535/51788187135_3cf8c03f70_o.gif",
        "title": "Cartoon"
      }
    ]
  },
  {
    "author": "ZanarkTempest",
    "link_thumb": "https://live.staticflickr.com/65535/51788187050_c688e0ce2c_o.gif",
    "link_bin": "https://github.com/lmbstudiocontact/mb6_1/raw/main/1918.bin",
    "id_bin": "1918",
    "list_language": [],
    "array_tags": [
      "sonic",
      "cartoon",
      "games"
    ],
    "list_album": [
      {
        "id_album": "-2075887794",
        "link_thumb": "https://live.staticflickr.com/65535/51788187050_c688e0ce2c_o.gif",
        "title": "Cartoon"
      }
    ]
  },
  {
    "author": "ZanarkTempest",
    "link_thumb": "https://live.staticflickr.com/65535/51787564138_5660f09143_o.gif",
    "link_bin": "https://github.com/lmbstudiocontact/mb6_1/raw/main/1919.bin",
    "id_bin": "1919",
    "list_language": [],
    "array_tags": [
      "sonic",
      "cartoon",
      "games"
    ],
    "list_album": [
      {
        "id_album": "-2075887794",
        "link_thumb": "https://live.staticflickr.com/65535/51787564138_5660f09143_o.gif",
        "title": "Cartoon"
      }
    ]
  },
  {
    "author": "ZanarkTempest",
    "link_thumb": "https://live.staticflickr.com/65535/51787564078_ed5a3731bc_o.gif",
    "link_bin": "https://github.com/lmbstudiocontact/mb6_1/raw/main/1923.bin",
    "id_bin": "1923",
    "list_language": [],
    "array_tags": [
      "games"
    ],
    "list_album": [
      {
        "id_album": "-2075887794",
        "link_thumb": "https://live.staticflickr.com/65535/51787564078_ed5a3731bc_o.gif",
        "title": "Cartoon"
      }
    ]
  },
  {
    "author": "ZanarkTempest",
    "link_thumb": "https://live.staticflickr.com/65535/51787938534_b513b5c7dc_o.gif",
    "link_bin": "https://github.com/lmbstudiocontact/mb6_1/raw/main/1924.bin",
    "id_bin": "1924",
    "list_language": [],
    "array_tags": [
      "game"
    ],
    "list_album": [
      {
        "id_album": "-2075887794",
        "link_thumb": "https://live.staticflickr.com/65535/51787938534_b513b5c7dc_o.gif",
        "title": "Cartoon"
      }
    ]
  },
  {
    "author": "ZanarkTempest",
    "link_thumb": "https://live.staticflickr.com/65535/51788186840_7a9be31abf_o.gif",
    "link_bin": "https://github.com/lmbstudiocontact/mb6_1/raw/main/1925.bin",
    "id_bin": "1925",
    "list_language": [],
    "array_tags": [
      "game"
    ],
    "list_album": [
      {
        "id_album": "-2075887794",
        "link_thumb": "https://live.staticflickr.com/65535/51788186840_7a9be31abf_o.gif",
        "title": "Cartoon"
      }
    ]
  },
  {
    "author": "ZanarkTempest",
    "link_thumb": "https://live.staticflickr.com/65535/51786496607_3419658771_o.gif",
    "link_bin": "https://github.com/lmbstudiocontact/mb6_1/raw/main/1926.bin",
    "id_bin": "1926",
    "list_language": [],
    "array_tags": [
      "game"
    ],
    "list_album": [
      {
        "id_album": "-2075887794",
        "link_thumb": "https://live.staticflickr.com/65535/51786496607_3419658771_o.gif",
        "title": "Cartoon"
      }
    ]
  },
  {
    "author": "ZanarkTempest",
    "link_thumb": "https://live.staticflickr.com/65535/51787938034_965eec395d_o.gif",
    "link_bin": "https://github.com/lmbstudiocontact/mb6_1/raw/main/1942.bin",
    "id_bin": "1942",
    "list_language": [],
    "array_tags": [
      "cartoon"
    ],
    "list_album": [
      {
        "id_album": "-2075887794",
        "link_thumb": "https://live.staticflickr.com/65535/51787938034_965eec395d_o.gif",
        "title": "Cartoon"
      }
    ]
  },
  {
    "author": "ZanarkTempest",
    "link_thumb": "https://live.staticflickr.com/65535/51789264086_7cda8be791_o.gif",
    "link_bin": "https://github.com/lmbstudiocontact/mb6_1/raw/main/1967.bin",
    "id_bin": "1967",
    "list_language": [],
    "array_tags": [
      "cartoon"
    ],
    "list_album": [
      {
        "id_album": "-2075887794",
        "link_thumb": "https://live.staticflickr.com/65535/51789264086_7cda8be791_o.gif",
        "title": "Cartoon"
      }
    ]
  },
  {
    "author": "ZanarkTempest",
    "link_thumb": "https://live.staticflickr.com/65535/51788185895_0eaf874779_o.gif",
    "link_bin": "https://github.com/lmbstudiocontact/mb6_1/raw/main/1968.bin",
    "id_bin": "1968",
    "list_language": [],
    "array_tags": [
      "cartoon"
    ],
    "list_album": [
      {
        "id_album": "-2075887794",
        "link_thumb": "https://live.staticflickr.com/65535/51788185895_0eaf874779_o.gif",
        "title": "Cartoon"
      }
    ]
  },
  {
    "author": "ZanarkTempest",
    "link_thumb": "https://live.staticflickr.com/65535/51787937439_a8aefe78df_o.gif",
    "link_bin": "https://github.com/lmbstudiocontact/mb6_1/raw/main/1969.bin",
    "id_bin": "1969",
    "list_language": [],
    "array_tags": [
      "cartoon"
    ],
    "list_album": [
      {
        "id_album": "-2075887794",
        "link_thumb": "https://live.staticflickr.com/65535/51787937439_a8aefe78df_o.gif",
        "title": "Cartoon"
      }
    ]
  },
  {
    "author": "ZanarkTempest",
    "link_thumb": "https://live.staticflickr.com/65535/51787562858_b65ea45d80_o.gif",
    "link_bin": "https://github.com/lmbstudiocontact/mb6_1/raw/main/1972.bin",
    "id_bin": "1972",
    "list_language": [],
    "array_tags": [
      "cartoon"
    ],
    "list_album": [
      {
        "id_album": "-2075887794",
        "link_thumb": "https://live.staticflickr.com/65535/51787562858_b65ea45d80_o.gif",
        "title": "Cartoon"
      }
    ]
  },
  {
    "author": "ZanarkTempest",
    "link_thumb": "https://live.staticflickr.com/65535/51787936779_c203c952cc_o.gif",
    "link_bin": "https://github.com/lmbstudiocontact/mb6_1/raw/main/1989.bin",
    "id_bin": "1989",
    "list_language": [],
    "array_tags": [
      "cartoon",
      "spacejam",
      "looneytunes"
    ],
    "list_album": [
      {
        "id_album": "-2075887794",
        "link_thumb": "https://live.staticflickr.com/65535/51787936779_c203c952cc_o.gif",
        "title": "Cartoon"
      }
    ]
  },
  {
    "author": "ZanarkTempest",
    "link_thumb": "https://live.staticflickr.com/65535/51787562193_7f9ff12339_o.gif",
    "link_bin": "https://github.com/lmbstudiocontact/mb6_1/raw/main/1990.bin",
    "id_bin": "1990",
    "list_language": [],
    "array_tags": [
      "cartoon",
      "spacejam",
      "looneytunes"
    ],
    "list_album": [
      {
        "id_album": "-2075887794",
        "link_thumb": "https://live.staticflickr.com/65535/51787562193_7f9ff12339_o.gif",
        "title": "Cartoon"
      }
    ]
  },
  {
    "author": "ZanarkTempest",
    "link_thumb": "https://live.staticflickr.com/65535/51787312821_53f2ca2a8f_o.gif",
    "link_bin": "https://github.com/lmbstudiocontact/mb6_1/raw/main/1991.bin",
    "id_bin": "1991",
    "list_language": [],
    "array_tags": [
      "cartoon",
      "spacejam",
      "looneytunes"
    ],
    "list_album": [
      {
        "id_album": "-2075887794",
        "link_thumb": "https://live.staticflickr.com/65535/51787312821_53f2ca2a8f_o.gif",
        "title": "Cartoon"
      }
    ]
  },
  {
    "author": "ZanarkTempest",
    "link_thumb": "https://live.staticflickr.com/65535/51787562068_ec06e335a3_o.gif",
    "link_bin": "https://github.com/lmbstudiocontact/mb6_1/raw/main/1992.bin",
    "id_bin": "1992",
    "list_language": [],
    "array_tags": [
      "cartoon",
      "spacejam",
      "looneytunes"
    ],
    "list_album": [
      {
        "id_album": "-2075887794",
        "link_thumb": "https://live.staticflickr.com/65535/51787562068_ec06e335a3_o.gif",
        "title": "Cartoon"
      }
    ]
  },
  {
    "author": "ZanarkTempest",
    "link_thumb": "https://live.staticflickr.com/65535/51788184495_bdbf42cc5c_o.gif",
    "link_bin": "https://github.com/lmbstudiocontact/mb6_1/raw/main/1993.bin",
    "id_bin": "1993",
    "list_language": [],
    "array_tags": [
      "cartoon",
      "spacejam",
      "looneytunes"
    ],
    "list_album": [
      {
        "id_album": "-2075887794",
        "link_thumb": "https://live.staticflickr.com/65535/51788184495_bdbf42cc5c_o.gif",
        "title": "Cartoon"
      }
    ]
  },
  {
    "author": "ZanarkTempest",
    "link_thumb": "https://live.staticflickr.com/65535/51787312626_047431b0d1_o.gif",
    "link_bin": "https://github.com/lmbstudiocontact/mb6_1/raw/main/1994.bin",
    "id_bin": "1994",
    "list_language": [],
    "array_tags": [
      "cartoon",
      "spacejam",
      "looneytunes"
    ],
    "list_album": [
      {
        "id_album": "-2075887794",
        "link_thumb": "https://live.staticflickr.com/65535/51787312626_047431b0d1_o.gif",
        "title": "Cartoon"
      }
    ]
  },
  {
    "author": "ZanarkTempest",
    "link_thumb": "https://live.staticflickr.com/65535/51787312531_fb3b577638_o.gif",
    "link_bin": "https://github.com/lmbstudiocontact/mb6_1/raw/main/1995.bin",
    "id_bin": "1995",
    "list_language": [],
    "array_tags": [
      "cartoon",
      "spacejam",
      "looneytunes"
    ],
    "list_album": [
      {
        "id_album": "-2075887794",
        "link_thumb": "https://live.staticflickr.com/65535/51787312531_fb3b577638_o.gif",
        "title": "Cartoon"
      }
    ]
  },
  {
    "author": "ZanarkTempest",
    "link_thumb": "https://live.staticflickr.com/65535/51787936229_54c666445b_o.gif",
    "link_bin": "https://github.com/lmbstudiocontact/mb6_1/raw/main/1996.bin",
    "id_bin": "1996",
    "list_language": [],
    "array_tags": [
      "cartoon",
      "spacejam",
      "looneytunes"
    ],
    "list_album": [
      {
        "id_album": "-2075887794",
        "link_thumb": "https://live.staticflickr.com/65535/51787936229_54c666445b_o.gif",
        "title": "Cartoon"
      }
    ]
  },
  {
    "author": "ZanarkTempest",
    "link_thumb": "https://live.staticflickr.com/65535/51787936174_3be418135f_o.gif",
    "link_bin": "https://github.com/lmbstudiocontact/mb6_1/raw/main/1997.bin",
    "id_bin": "1997",
    "list_language": [],
    "array_tags": [
      "cartoon",
      "spacejam",
      "looneytunes"
    ],
    "list_album": [
      {
        "id_album": "-2075887794",
        "link_thumb": "https://live.staticflickr.com/65535/51787936174_3be418135f_o.gif",
        "title": "Cartoon"
      }
    ]
  },
  {
    "author": "ZanarkTempest",
    "link_thumb": "https://live.staticflickr.com/65535/51788184110_04a09e4403_o.gif",
    "link_bin": "https://github.com/lmbstudiocontact/mb6_1/raw/main/1998.bin",
    "id_bin": "1998",
    "list_language": [],
    "array_tags": [
      "cartoon",
      "spacejam",
      "looneytunes"
    ],
    "list_album": [
      {
        "id_album": "-2075887794",
        "link_thumb": "https://live.staticflickr.com/65535/51788184110_04a09e4403_o.gif",
        "title": "Cartoon"
      }
    ]
  },
  {
    "author": "ZanarkTempest",
    "link_thumb": "https://live.staticflickr.com/65535/51787561633_9c004a9172_o.gif",
    "link_bin": "https://github.com/lmbstudiocontact/mb6_1/raw/main/1999.bin",
    "id_bin": "1999",
    "list_language": [],
    "array_tags": [
      "cartoon",
      "spacejam",
      "looneytunes"
    ],
    "list_album": [
      {
        "id_album": "-2075887794",
        "link_thumb": "https://live.staticflickr.com/65535/51787561633_9c004a9172_o.gif",
        "title": "Cartoon"
      }
    ]
  },
  {
    "author": "ZanarkTempest",
    "link_thumb": "https://live.staticflickr.com/65535/51788184020_a67006f5cb_o.gif",
    "link_bin": "https://github.com/lmbstudiocontact/mb6_1/raw/main/2000.bin",
    "id_bin": "2000",
    "list_language": [],
    "array_tags": [
      "cartoon",
      "spacejam",
      "looneytunes"
    ],
    "list_album": [
      {
        "id_album": "-2075887794",
        "link_thumb": "https://live.staticflickr.com/65535/51788184020_a67006f5cb_o.gif",
        "title": "Cartoon"
      }
    ]
  },
  {
    "author": "ZanarkTempest",
    "link_thumb": "https://live.staticflickr.com/65535/51787312236_1deaa6ef24_o.gif",
    "link_bin": "https://github.com/lmbstudiocontact/mb6_1/raw/main/2001.bin",
    "id_bin": "2001",
    "list_language": [],
    "array_tags": [
      "cartoon",
      "spacejam",
      "looneytunes"
    ],
    "list_album": [
      {
        "id_album": "-2075887794",
        "link_thumb": "https://live.staticflickr.com/65535/51787312236_1deaa6ef24_o.gif",
        "title": "Cartoon"
      }
    ]
  },
  {
    "author": "ZanarkTempest",
    "link_thumb": "https://live.staticflickr.com/65535/51789392543_ec540a61da_o.gif",
    "link_bin": "https://github.com/lmbstudiocontact/mb6_1/raw/main/2006.bin",
    "id_bin": "2006",
    "list_language": [],
    "array_tags": [
      "anime"
    ],
    "list_album": [
      {
        "id_album": "-2075887794",
        "link_thumb": "https://live.staticflickr.com/65535/51789392543_ec540a61da_o.gif",
        "title": "Cartoon"
      }
    ]
  },
  {
    "author": "ZanarkTempest",
    "link_thumb": "https://live.staticflickr.com/65535/51790012645_a8b98247e2_o.gif",
    "link_bin": "https://github.com/lmbstudiocontact/mb6_1/raw/main/2008.bin",
    "id_bin": "2008",
    "list_language": [],
    "array_tags": [
      "anime"
    ],
    "list_album": [
      {
        "id_album": "-2075887794",
        "link_thumb": "https://live.staticflickr.com/65535/51790012645_a8b98247e2_o.gif",
        "title": "Cartoon"
      }
    ]
  },
  {
    "author": "ZanarkTempest",
    "link_thumb": "https://live.staticflickr.com/65535/51788183615_fc95e3167f_o.gif",
    "link_bin": "https://github.com/lmbstudiocontact/mb6_1/raw/main/2009.bin",
    "id_bin": "2009",
    "list_language": [],
    "array_tags": [
      "anime"
    ],
    "list_album": [
      {
        "id_album": "-2075887794",
        "link_thumb": "https://live.staticflickr.com/65535/51788183615_fc95e3167f_o.gif",
        "title": "Cartoon"
      }
    ]
  },
  {
    "author": "ZanarkTempest",
    "link_thumb": "https://live.staticflickr.com/65535/51787561113_6b701fb1b6_o.gif",
    "link_bin": "https://github.com/lmbstudiocontact/mb6_1/raw/main/2010.bin",
    "id_bin": "2010",
    "list_language": [],
    "array_tags": [
      "anime"
    ],
    "list_album": [
      {
        "id_album": "-2075887794",
        "link_thumb": "https://live.staticflickr.com/65535/51787561113_6b701fb1b6_o.gif",
        "title": "Cartoon"
      }
    ]
  },
  {
    "author": "ZanarkTempest",
    "link_thumb": "https://live.staticflickr.com/65535/51787560973_c9c692b15a_o.gif",
    "link_bin": "https://github.com/lmbstudiocontact/mb6_1/raw/main/2011.bin",
    "id_bin": "2011",
    "list_language": [],
    "array_tags": [
      "anime"
    ],
    "list_album": [
      {
        "id_album": "-2075887794",
        "link_thumb": "https://live.staticflickr.com/65535/51787560973_c9c692b15a_o.gif",
        "title": "Cartoon"
      }
    ]
  },
  {
    "author": "ZanarkTempest",
    "link_thumb": "https://live.staticflickr.com/65535/51787308986_1cf7864297_o.gif",
    "link_bin": "https://github.com/lmbstudiocontact/mb6_1/raw/main/2105.bin",
    "id_bin": "2105",
    "list_language": [],
    "array_tags": [
      "marvel",
      "heartrate",
      "pulse"
    ],
    "list_album": [
      {
        "id_album": "-2075887794",
        "link_thumb": "https://live.staticflickr.com/65535/51787308986_1cf7864297_o.gif",
        "title": "Cartoon"
      }
    ]
  },
  {
    "author": "ZanarkTempest",
    "link_thumb": "https://live.staticflickr.com/65535/51787556998_f89acfa074_o.gif",
    "link_bin": "https://github.com/lmbstudiocontact/mb6_1/raw/main/2146.bin",
    "id_bin": "2146",
    "list_language": [],
    "array_tags": [
      "heartrate",
      "anime"
    ],
    "list_album": [
      {
        "id_album": "-2075887794",
        "link_thumb": "https://live.staticflickr.com/65535/51787556998_f89acfa074_o.gif",
        "title": "Cartoon"
      }
    ]
  },
  {
    "author": "ZanarkTempest",
    "link_thumb": "https://live.staticflickr.com/65535/51787930404_c3c644d7d1_o.gif",
    "link_bin": "https://github.com/lmbstudiocontact/mb6_1/raw/main/2190.bin",
    "id_bin": "2190",
    "list_language": [],
    "array_tags": [
      "heartrate",
      "steps"
    ],
    "list_album": [
      {
        "id_album": "-2075887794",
        "link_thumb": "https://live.staticflickr.com/65535/51787930404_c3c644d7d1_o.gif",
        "title": "Cartoon"
      }
    ]
  }
]