[
  {
    "author": "LMB Studio",
    "link_thumb": "https://live.staticflickr.com/65535/51677472504_01bd1c6c93_o.gif",
    "link_bin": "https://github.com/lmbstudiocontact/mb6_2/raw/main/GhibliAnime0_M6_2.bin",
    "id_bin": "GhibliAnime0_M6_2",
    "list_language": [
      {
        "author": "LMB Studio",
        "link_thumb": "https://live.staticflickr.com/65535/51676800651_3e3c2e1863_o.gif",
        "link_bin": "https://github.com/lmbstudiocontact/mb6_2/raw/main/GhibliAnime0_M6_2_English.bin",
        "name_language": "English",
        "id_bin_language": "GhibliAnime0_M6_2_English"
      },
      {
        "author": "LMB Studio",
        "link_thumb": "https://live.staticflickr.com/65535/51677047933_028f83280a_o.gif",
        "link_bin": "https://github.com/lmbstudiocontact/mb6_2/raw/main/GhibliAnime0_M6_2_Portuguese.bin",
        "name_language": "Portuguese",
        "id_bin_language": "GhibliAnime0_M6_2_Portuguese"
      },
      {
        "author": "LMB Studio",
        "link_thumb": "https://live.staticflickr.com/65535/51675998242_cc17a841d0_o.gif",
        "link_bin": "https://github.com/lmbstudiocontact/mb6_2/raw/main/GhibliAnime0_M6_2_Russian.bin",
        "name_language": "Russian",
        "id_bin_language": "GhibliAnime0_M6_2_Russian"
      },
      {
        "author": "LMB Studio",
        "link_thumb": "https://live.staticflickr.com/65535/51675998487_45a60cba1e_o.gif",
        "link_bin": "https://github.com/lmbstudiocontact/mb6_2/raw/main/GhibliAnime0_M6_2_Spanish.bin",
        "name_language": "Spanish",
        "id_bin_language": "GhibliAnime0_M6_2_Spanish"
      }
    ],
    "array_tags": [
      "lmbstudio"
    ],
    "list_album": [
      {
        "id_album": "1193703152",
        "link_thumb": "https://live.staticflickr.com/65535/51677472504_01bd1c6c93_o.gif",
        "title": "Ghibli Anime_M6_2"
      }
    ]
  },
  {
    "author": "LMB Studio",
    "link_thumb": "https://live.staticflickr.com/65535/51677683770_4d47b96c55_o.gif",
    "link_bin": "https://github.com/lmbstudiocontact/mb6_2/raw/main/GhibliAnime10_M6_2.bin",
    "id_bin": "GhibliAnime10_M6_2",
    "list_language": [
      {
        "author": "LMB Studio",
        "link_thumb": "https://live.staticflickr.com/65535/51675998882_9c91c51e6c_o.gif",
        "link_bin": "https://github.com/lmbstudiocontact/mb6_2/raw/main/GhibliAnime10_M6_2_English.bin",
        "name_language": "English",
        "id_bin_language": "GhibliAnime10_M6_2_English"
      },
      {
        "author": "LMB Studio",
        "link_thumb": "https://live.staticflickr.com/65535/51677048938_e8f922ca65_o.gif",
        "link_bin": "https://github.com/lmbstudiocontact/mb6_2/raw/main/GhibliAnime10_M6_2_Portuguese.bin",
        "name_language": "Portuguese",
        "id_bin_language": "GhibliAnime10_M6_2_Portuguese"
      },
      {
        "author": "LMB Studio",
        "link_thumb": "https://live.staticflickr.com/65535/51677474094_91ae4ced5c_o.gif",
        "link_bin": "https://github.com/lmbstudiocontact/mb6_2/raw/main/GhibliAnime10_M6_2_Russian.bin",
        "name_language": "Russian",
        "id_bin_language": "GhibliAnime10_M6_2_Russian"
      },
      {
        "author": "LMB Studio",
        "link_thumb": "https://live.staticflickr.com/65535/51677684700_75d52cf91e_o.gif",
        "link_bin": "https://github.com/lmbstudiocontact/mb6_2/raw/main/GhibliAnime10_M6_2_Spanish.bin",
        "name_language": "Spanish",
        "id_bin_language": "GhibliAnime10_M6_2_Spanish"
      }
    ],
    "array_tags": [
      "lmbstudio"
    ],
    "list_album": [
      {
        "id_album": "1193703152",
        "link_thumb": "https://live.staticflickr.com/65535/51677683770_4d47b96c55_o.gif",
        "title": "Ghibli Anime_M6_2"
      }
    ]
  },
  {
    "author": "LMB Studio",
    "link_thumb": "https://live.staticflickr.com/65535/51677684955_de1b9e59d3_o.gif",
    "link_bin": "https://github.com/lmbstudiocontact/mb6_2/raw/main/GhibliAnime11_M6_2.bin",
    "id_bin": "GhibliAnime11_M6_2",
    "list_language": [
      {
        "author": "LMB Studio",
        "link_thumb": "https://live.staticflickr.com/65535/51675999942_ca66126292_o.gif",
        "link_bin": "https://github.com/lmbstudiocontact/mb6_2/raw/main/GhibliAnime11_M6_2_English.bin",
        "name_language": "English",
        "id_bin_language": "GhibliAnime11_M6_2_English"
      },
      {
        "author": "LMB Studio",
        "link_thumb": "https://live.staticflickr.com/65535/51677685365_65acb72a49_o.gif",
        "link_bin": "https://github.com/lmbstudiocontact/mb6_2/raw/main/GhibliAnime11_M6_2_Portuguese.bin",
        "name_language": "Portuguese",
        "id_bin_language": "GhibliAnime11_M6_2_Portuguese"
      },
      {
        "author": "LMB Studio",
        "link_thumb": "https://live.staticflickr.com/65535/51677475144_fd0bea1595_o.gif",
        "link_bin": "https://github.com/lmbstudiocontact/mb6_2/raw/main/GhibliAnime11_M6_2_Russian.bin",
        "name_language": "Russian",
        "id_bin_language": "GhibliAnime11_M6_2_Russian"
      },
      {
        "author": "LMB Studio",
        "link_thumb": "https://live.staticflickr.com/65535/51677685860_f306bc9f34_o.gif",
        "link_bin": "https://github.com/lmbstudiocontact/mb6_2/raw/main/GhibliAnime11_M6_2_Spanish.bin",
        "name_language": "Spanish",
        "id_bin_language": "GhibliAnime11_M6_2_Spanish"
      }
    ],
    "array_tags": [
      "lmbstudio"
    ],
    "list_album": [
      {
        "id_album": "1193703152",
        "link_thumb": "https://live.staticflickr.com/65535/51677684955_de1b9e59d3_o.gif",
        "title": "Ghibli Anime_M6_2"
      }
    ]
  },
  {
    "author": "LMB Studio",
    "link_thumb": "https://live.staticflickr.com/65535/51677050898_59d5080aed_o.gif",
    "link_bin": "https://github.com/lmbstudiocontact/mb6_2/raw/main/GhibliAnime12_M6_2.bin",
    "id_bin": "GhibliAnime12_M6_2",
    "list_language": [
      {
        "author": "LMB Studio",
        "link_thumb": "https://live.staticflickr.com/65535/51677686415_62d0a2f810_o.gif",
        "link_bin": "https://github.com/lmbstudiocontact/mb6_2/raw/main/GhibliAnime12_M6_2_English.bin",
        "name_language": "English",
        "id_bin_language": "GhibliAnime12_M6_2_English"
      },
      {
        "author": "LMB Studio",
        "link_thumb": "https://live.staticflickr.com/65535/51676804066_127cf329db_o.gif",
        "link_bin": "https://github.com/lmbstudiocontact/mb6_2/raw/main/GhibliAnime12_M6_2_Portuguese.bin",
        "name_language": "Portuguese",
        "id_bin_language": "GhibliAnime12_M6_2_Portuguese"
      },
      {
        "author": "LMB Studio",
        "link_thumb": "https://live.staticflickr.com/65535/51677686825_248e8e2196_o.gif",
        "link_bin": "https://github.com/lmbstudiocontact/mb6_2/raw/main/GhibliAnime12_M6_2_Russian.bin",
        "name_language": "Russian",
        "id_bin_language": "GhibliAnime12_M6_2_Russian"
      },
      {
        "author": "LMB Studio",
        "link_thumb": "https://live.staticflickr.com/65535/51678573525_5a7b4b62c9_o.gif",
        "link_bin": "https://github.com/lmbstudiocontact/mb6_2/raw/main/GhibliAnime12_M6_2_Spanish.bin",
        "name_language": "Spanish",
        "id_bin_language": "GhibliAnime12_M6_2_Spanish"
      }
    ],
    "array_tags": [
      "lmbstudio"
    ],
    "list_album": [
      {
        "id_album": "1193703152",
        "link_thumb": "https://live.staticflickr.com/65535/51677050898_59d5080aed_o.gif",
        "title": "Ghibli Anime_M6_2"
      }
    ]
  },
  {
    "author": "LMB Studio",
    "link_thumb": "https://live.staticflickr.com/65535/51677688910_beb61588ee_o.gif",
    "link_bin": "https://github.com/lmbstudiocontact/mb6_2/raw/main/GhibliAnime13_M6_2.bin",
    "id_bin": "GhibliAnime13_M6_2",
    "list_language": [
      {
        "author": "LMB Studio",
        "link_thumb": "https://live.staticflickr.com/65535/51676003787_03d6e2c86e_o.gif",
        "link_bin": "https://github.com/lmbstudiocontact/mb6_2/raw/main/GhibliAnime13_M6_2_English.bin",
        "name_language": "English",
        "id_bin_language": "GhibliAnime13_M6_2_English"
      },
      {
        "author": "LMB Studio",
        "link_thumb": "https://live.staticflickr.com/65535/51676806851_4a31fecd55_o.gif",
        "link_bin": "https://github.com/lmbstudiocontact/mb6_2/raw/main/GhibliAnime13_M6_2_Portuguese.bin",
        "name_language": "Portuguese",
        "id_bin_language": "GhibliAnime13_M6_2_Portuguese"
      },
      {
        "author": "LMB Studio",
        "link_thumb": "https://live.staticflickr.com/65535/51677689810_0b12802153_o.gif",
        "link_bin": "https://github.com/lmbstudiocontact/mb6_2/raw/main/GhibliAnime13_M6_2_Russian.bin",
        "name_language": "Russian",
        "id_bin_language": "GhibliAnime13_M6_2_Russian"
      },
      {
        "author": "LMB Studio",
        "link_thumb": "https://live.staticflickr.com/65535/51677054728_34366d1c5b_o.gif",
        "link_bin": "https://github.com/lmbstudiocontact/mb6_2/raw/main/GhibliAnime13_M6_2_Spanish.bin",
        "name_language": "Spanish",
        "id_bin_language": "GhibliAnime13_M6_2_Spanish"
      }
    ],
    "array_tags": [
      "lmbstudio"
    ],
    "list_album": [
      {
        "id_album": "1193703152",
        "link_thumb": "https://live.staticflickr.com/65535/51677688910_beb61588ee_o.gif",
        "title": "Ghibli Anime_M6_2"
      }
    ]
  },
  {
    "author": "LMB Studio",
    "link_thumb": "https://live.staticflickr.com/65535/51676807541_42d53930a1_o.gif",
    "link_bin": "https://github.com/lmbstudiocontact/mb6_2/raw/main/GhibliAnime14_M6_2.bin",
    "id_bin": "GhibliAnime14_M6_2",
    "list_language": [
      {
        "author": "LMB Studio",
        "link_thumb": "https://live.staticflickr.com/65535/51676807796_aafe4109a6_o.gif",
        "link_bin": "https://github.com/lmbstudiocontact/mb6_2/raw/main/GhibliAnime14_M6_2_English.bin",
        "name_language": "English",
        "id_bin_language": "GhibliAnime14_M6_2_English"
      },
      {
        "author": "LMB Studio",
        "link_thumb": "https://live.staticflickr.com/65535/51677480019_c7c4c93940_o.gif",
        "link_bin": "https://github.com/lmbstudiocontact/mb6_2/raw/main/GhibliAnime14_M6_2_Portuguese.bin",
        "name_language": "Portuguese",
        "id_bin_language": "GhibliAnime14_M6_2_Portuguese"
      },
      {
        "author": "LMB Studio",
        "link_thumb": "https://live.staticflickr.com/65535/51676808131_2b8995de9a_o.gif",
        "link_bin": "https://github.com/lmbstudiocontact/mb6_2/raw/main/GhibliAnime14_M6_2_Russian.bin",
        "name_language": "Russian",
        "id_bin_language": "GhibliAnime14_M6_2_Russian"
      },
      {
        "author": "LMB Studio",
        "link_thumb": "https://live.staticflickr.com/65535/51677055798_fd4a2f9c21_o.gif",
        "link_bin": "https://github.com/lmbstudiocontact/mb6_2/raw/main/GhibliAnime14_M6_2_Spanish.bin",
        "name_language": "Spanish",
        "id_bin_language": "GhibliAnime14_M6_2_Spanish"
      }
    ],
    "array_tags": [
      "lmbstudio"
    ],
    "list_album": [
      {
        "id_album": "1193703152",
        "link_thumb": "https://live.staticflickr.com/65535/51676807541_42d53930a1_o.gif",
        "title": "Ghibli Anime_M6_2"
      }
    ]
  },
  {
    "author": "LMB Studio",
    "link_thumb": "https://live.staticflickr.com/65535/51676808486_022b269326_o.gif",
    "link_bin": "https://github.com/lmbstudiocontact/mb6_2/raw/main/GhibliAnime15_M6_2.bin",
    "id_bin": "GhibliAnime15_M6_2",
    "list_language": [
      {
        "author": "LMB Studio",
        "link_thumb": "https://live.staticflickr.com/65535/51676808696_a62507bee7_o.gif",
        "link_bin": "https://github.com/lmbstudiocontact/mb6_2/raw/main/GhibliAnime15_M6_2_English.bin",
        "name_language": "English",
        "id_bin_language": "GhibliAnime15_M6_2_English"
      },
      {
        "author": "LMB Studio",
        "link_thumb": "https://live.staticflickr.com/65535/51677056353_ea6185f133_o.gif",
        "link_bin": "https://github.com/lmbstudiocontact/mb6_2/raw/main/GhibliAnime15_M6_2_Portuguese.bin",
        "name_language": "Portuguese",
        "id_bin_language": "GhibliAnime15_M6_2_Portuguese"
      },
      {
        "author": "LMB Studio",
        "link_thumb": "https://live.staticflickr.com/65535/51676809136_d941564961_o.gif",
        "link_bin": "https://github.com/lmbstudiocontact/mb6_2/raw/main/GhibliAnime15_M6_2_Russian.bin",
        "name_language": "Russian",
        "id_bin_language": "GhibliAnime15_M6_2_Russian"
      },
      {
        "author": "LMB Studio",
        "link_thumb": "https://live.staticflickr.com/65535/51677481384_87a3e2f98d_o.gif",
        "link_bin": "https://github.com/lmbstudiocontact/mb6_2/raw/main/GhibliAnime15_M6_2_Spanish.bin",
        "name_language": "Spanish",
        "id_bin_language": "GhibliAnime15_M6_2_Spanish"
      }
    ],
    "array_tags": [
      "lmbstudio"
    ],
    "list_album": [
      {
        "id_album": "1193703152",
        "link_thumb": "https://live.staticflickr.com/65535/51676808486_022b269326_o.gif",
        "title": "Ghibli Anime_M6_2"
      }
    ]
  },
  {
    "author": "LMB Studio",
    "link_thumb": "https://live.staticflickr.com/65535/51677481584_54e6598c4f_o.gif",
    "link_bin": "https://github.com/lmbstudiocontact/mb6_2/raw/main/GhibliAnime16_M6_2.bin",
    "id_bin": "GhibliAnime16_M6_2",
    "list_language": [
      {
        "author": "LMB Studio",
        "link_thumb": "https://live.staticflickr.com/65535/51677692330_0e8130c2f4_o.gif",
        "link_bin": "https://github.com/lmbstudiocontact/mb6_2/raw/main/GhibliAnime16_M6_2_English.bin",
        "name_language": "English",
        "id_bin_language": "GhibliAnime16_M6_2_English"
      },
      {
        "author": "LMB Studio",
        "link_thumb": "https://live.staticflickr.com/65535/51677692610_5902922f48_o.gif",
        "link_bin": "https://github.com/lmbstudiocontact/mb6_2/raw/main/GhibliAnime16_M6_2_Portuguese.bin",
        "name_language": "Portuguese",
        "id_bin_language": "GhibliAnime16_M6_2_Portuguese"
      },
      {
        "author": "LMB Studio",
        "link_thumb": "https://live.staticflickr.com/65535/51677057753_06f96cff47_o.gif",
        "link_bin": "https://github.com/lmbstudiocontact/mb6_2/raw/main/GhibliAnime16_M6_2_Russian.bin",
        "name_language": "Russian",
        "id_bin_language": "GhibliAnime16_M6_2_Russian"
      },
      {
        "author": "LMB Studio",
        "link_thumb": "https://live.staticflickr.com/65535/51677057958_ea905c88c8_o.gif",
        "link_bin": "https://github.com/lmbstudiocontact/mb6_2/raw/main/GhibliAnime16_M6_2_Spanish.bin",
        "name_language": "Spanish",
        "id_bin_language": "GhibliAnime16_M6_2_Spanish"
      }
    ],
    "array_tags": [
      "lmbstudio"
    ],
    "list_album": [
      {
        "id_album": "1193703152",
        "link_thumb": "https://live.staticflickr.com/65535/51677481584_54e6598c4f_o.gif",
        "title": "Ghibli Anime_M6_2"
      }
    ]
  },
  {
    "author": "LMB Studio",
    "link_thumb": "https://live.staticflickr.com/65535/51677693305_2663064a40_o.gif",
    "link_bin": "https://github.com/lmbstudiocontact/mb6_2/raw/main/GhibliAnime1_M6_2.bin",
    "id_bin": "GhibliAnime1_M6_2",
    "list_language": [
      {
        "author": "LMB Studio",
        "link_thumb": "https://live.staticflickr.com/65535/51677693495_1e7aa2acd0_o.gif",
        "link_bin": "https://github.com/lmbstudiocontact/mb6_2/raw/main/GhibliAnime1_M6_2_English.bin",
        "name_language": "English",
        "id_bin_language": "GhibliAnime1_M6_2_English"
      },
      {
        "author": "LMB Studio",
        "link_thumb": "https://live.staticflickr.com/65535/51677058653_9b55378e2a_o.gif",
        "link_bin": "https://github.com/lmbstudiocontact/mb6_2/raw/main/GhibliAnime1_M6_2_Portuguese.bin",
        "name_language": "Portuguese",
        "id_bin_language": "GhibliAnime1_M6_2_Portuguese"
      },
      {
        "author": "LMB Studio",
        "link_thumb": "https://live.staticflickr.com/65535/51677483274_772a3923f6_o.gif",
        "link_bin": "https://github.com/lmbstudiocontact/mb6_2/raw/main/GhibliAnime1_M6_2_Russian.bin",
        "name_language": "Russian",
        "id_bin_language": "GhibliAnime1_M6_2_Russian"
      },
      {
        "author": "LMB Studio",
        "link_thumb": "https://live.staticflickr.com/65535/51676811536_b6dedfb56b_o.gif",
        "link_bin": "https://github.com/lmbstudiocontact/mb6_2/raw/main/GhibliAnime1_M6_2_Spanish.bin",
        "name_language": "Spanish",
        "id_bin_language": "GhibliAnime1_M6_2_Spanish"
      }
    ],
    "array_tags": [
      "lmbstudio"
    ],
    "list_album": [
      {
        "id_album": "1193703152",
        "link_thumb": "https://live.staticflickr.com/65535/51677693305_2663064a40_o.gif",
        "title": "Ghibli Anime_M6_2"
      }
    ]
  },
  {
    "author": "LMB Studio",
    "link_thumb": "https://live.staticflickr.com/65535/51676811686_94e85c7b68_o.gif",
    "link_bin": "https://github.com/lmbstudiocontact/mb6_2/raw/main/GhibliAnime2_M6_2.bin",
    "id_bin": "GhibliAnime2_M6_2",
    "list_language": [
      {
        "author": "LMB Studio",
        "link_thumb": "https://live.staticflickr.com/65535/51676811901_8901954375_o.gif",
        "link_bin": "https://github.com/lmbstudiocontact/mb6_2/raw/main/GhibliAnime2_M6_2_English.bin",
        "name_language": "English",
        "id_bin_language": "GhibliAnime2_M6_2_English"
      },
      {
        "author": "LMB Studio",
        "link_thumb": "https://live.staticflickr.com/65535/51677059623_fcc909602d_o.gif",
        "link_bin": "https://github.com/lmbstudiocontact/mb6_2/raw/main/GhibliAnime2_M6_2_Portuguese.bin",
        "name_language": "Portuguese",
        "id_bin_language": "GhibliAnime2_M6_2_Portuguese"
      },
      {
        "author": "LMB Studio",
        "link_thumb": "https://live.staticflickr.com/65535/51677059833_d331403588_o.gif",
        "link_bin": "https://github.com/lmbstudiocontact/mb6_2/raw/main/GhibliAnime2_M6_2_Russian.bin",
        "name_language": "Russian",
        "id_bin_language": "GhibliAnime2_M6_2_Russian"
      },
      {
        "author": "LMB Studio",
        "link_thumb": "https://live.staticflickr.com/65535/51677695155_77b0927332_o.gif",
        "link_bin": "https://github.com/lmbstudiocontact/mb6_2/raw/main/GhibliAnime2_M6_2_Spanish.bin",
        "name_language": "Spanish",
        "id_bin_language": "GhibliAnime2_M6_2_Spanish"
      }
    ],
    "array_tags": [
      "lmbstudio"
    ],
    "list_album": [
      {
        "id_album": "1193703152",
        "link_thumb": "https://live.staticflickr.com/65535/51676811686_94e85c7b68_o.gif",
        "title": "Ghibli Anime_M6_2"
      }
    ]
  },
  {
    "author": "LMB Studio",
    "link_thumb": "https://live.staticflickr.com/65535/51676010507_72bcc7703e_o.gif",
    "link_bin": "https://github.com/lmbstudiocontact/mb6_2/raw/main/GhibliAnime3_M6_2.bin",
    "id_bin": "GhibliAnime3_M6_2",
    "list_language": [
      {
        "author": "LMB Studio",
        "link_thumb": "https://live.staticflickr.com/65535/51677485259_f8bed004c6_o.gif",
        "link_bin": "https://github.com/lmbstudiocontact/mb6_2/raw/main/GhibliAnime3_M6_2_English.bin",
        "name_language": "English",
        "id_bin_language": "GhibliAnime3_M6_2_English"
      },
      {
        "author": "LMB Studio",
        "link_thumb": "https://live.staticflickr.com/65535/51677060738_fb4737b928_o.gif",
        "link_bin": "https://github.com/lmbstudiocontact/mb6_2/raw/main/GhibliAnime3_M6_2_Portuguese.bin",
        "name_language": "Portuguese",
        "id_bin_language": "GhibliAnime3_M6_2_Portuguese"
      },
      {
        "author": "LMB Studio",
        "link_thumb": "https://live.staticflickr.com/65535/51676011172_1da55cf1dc_o.gif",
        "link_bin": "https://github.com/lmbstudiocontact/mb6_2/raw/main/GhibliAnime3_M6_2_Russian.bin",
        "name_language": "Russian",
        "id_bin_language": "GhibliAnime3_M6_2_Russian"
      },
      {
        "author": "LMB Studio",
        "link_thumb": "https://live.staticflickr.com/65535/51677061248_345e20a9f2_o.gif",
        "link_bin": "https://github.com/lmbstudiocontact/mb6_2/raw/main/GhibliAnime3_M6_2_Spanish.bin",
        "name_language": "Spanish",
        "id_bin_language": "GhibliAnime3_M6_2_Spanish"
      }
    ],
    "array_tags": [
      "lmbstudio"
    ],
    "list_album": [
      {
        "id_album": "1193703152",
        "link_thumb": "https://live.staticflickr.com/65535/51676010507_72bcc7703e_o.gif",
        "title": "Ghibli Anime_M6_2"
      }
    ]
  },
  {
    "author": "LMB Studio",
    "link_thumb": "https://live.staticflickr.com/65535/51677486469_3f9a9eb3f4_o.gif",
    "link_bin": "https://github.com/lmbstudiocontact/mb6_2/raw/main/GhibliAnime4_M6_2.bin",
    "id_bin": "GhibliAnime4_M6_2",
    "list_language": [
      {
        "author": "LMB Studio",
        "link_thumb": "https://live.staticflickr.com/65535/51676011877_79fd2ffa63_o.gif",
        "link_bin": "https://github.com/lmbstudiocontact/mb6_2/raw/main/GhibliAnime4_M6_2_English.bin",
        "name_language": "English",
        "id_bin_language": "GhibliAnime4_M6_2_English"
      },
      {
        "author": "LMB Studio",
        "link_thumb": "https://live.staticflickr.com/65535/51677062278_38c497e4e2_o.gif",
        "link_bin": "https://github.com/lmbstudiocontact/mb6_2/raw/main/GhibliAnime4_M6_2_Portuguese.bin",
        "name_language": "Portuguese",
        "id_bin_language": "GhibliAnime4_M6_2_Portuguese"
      },
      {
        "author": "LMB Studio",
        "link_thumb": "https://live.staticflickr.com/65535/51677487234_6d424fb6d3_o.gif",
        "link_bin": "https://github.com/lmbstudiocontact/mb6_2/raw/main/GhibliAnime4_M6_2_Russian.bin",
        "name_language": "Russian",
        "id_bin_language": "GhibliAnime4_M6_2_Russian"
      },
      {
        "author": "LMB Studio",
        "link_thumb": "https://live.staticflickr.com/65535/51677487504_e8dc3caf4c_o.gif",
        "link_bin": "https://github.com/lmbstudiocontact/mb6_2/raw/main/GhibliAnime4_M6_2_Spanish.bin",
        "name_language": "Spanish",
        "id_bin_language": "GhibliAnime4_M6_2_Spanish"
      }
    ],
    "array_tags": [
      "lmbstudio"
    ],
    "list_album": [
      {
        "id_album": "1193703152",
        "link_thumb": "https://live.staticflickr.com/65535/51677486469_3f9a9eb3f4_o.gif",
        "title": "Ghibli Anime_M6_2"
      }
    ]
  },
  {
    "author": "LMB Studio",
    "link_thumb": "https://live.staticflickr.com/65535/51677487799_af8dd1236b_o.gif",
    "link_bin": "https://github.com/lmbstudiocontact/mb6_2/raw/main/GhibliAnime5_M6_2.bin",
    "id_bin": "GhibliAnime5_M6_2",
    "list_language": [
      {
        "author": "LMB Studio",
        "link_thumb": "https://live.staticflickr.com/65535/51676815711_068ce8e23c_o.gif",
        "link_bin": "https://github.com/lmbstudiocontact/mb6_2/raw/main/GhibliAnime5_M6_2_English.bin",
        "name_language": "English",
        "id_bin_language": "GhibliAnime5_M6_2_English"
      },
      {
        "author": "LMB Studio",
        "link_thumb": "https://live.staticflickr.com/65535/51676013452_9893ceb8db_o.gif",
        "link_bin": "https://github.com/lmbstudiocontact/mb6_2/raw/main/GhibliAnime5_M6_2_Portuguese.bin",
        "name_language": "Portuguese",
        "id_bin_language": "GhibliAnime5_M6_2_Portuguese"
      },
      {
        "author": "LMB Studio",
        "link_thumb": "https://live.staticflickr.com/65535/51676013672_150e4cd091_o.gif",
        "link_bin": "https://github.com/lmbstudiocontact/mb6_2/raw/main/GhibliAnime5_M6_2_Russian.bin",
        "name_language": "Russian",
        "id_bin_language": "GhibliAnime5_M6_2_Russian"
      },
      {
        "author": "LMB Studio",
        "link_thumb": "https://live.staticflickr.com/65535/51676816521_178ac91c6c_o.gif",
        "link_bin": "https://github.com/lmbstudiocontact/mb6_2/raw/main/GhibliAnime5_M6_2_Spanish.bin",
        "name_language": "Spanish",
        "id_bin_language": "GhibliAnime5_M6_2_Spanish"
      }
    ],
    "array_tags": [
      "lmbstudio"
    ],
    "list_album": [
      {
        "id_album": "1193703152",
        "link_thumb": "https://live.staticflickr.com/65535/51677487799_af8dd1236b_o.gif",
        "title": "Ghibli Anime_M6_2"
      }
    ]
  },
  {
    "author": "LMB Studio",
    "link_thumb": "https://live.staticflickr.com/65535/51676014262_a67fdcecfa_o.gif",
    "link_bin": "https://github.com/lmbstudiocontact/mb6_2/raw/main/GhibliAnime6_M6_2.bin",
    "id_bin": "GhibliAnime6_M6_2",
    "list_language": [
      {
        "author": "LMB Studio",
        "link_thumb": "https://live.staticflickr.com/65535/51676817166_1caf3ef025_o.gif",
        "link_bin": "https://github.com/lmbstudiocontact/mb6_2/raw/main/GhibliAnime6_M6_2_English.bin",
        "name_language": "English",
        "id_bin_language": "GhibliAnime6_M6_2_English"
      },
      {
        "author": "LMB Studio",
        "link_thumb": "https://live.staticflickr.com/65535/51677064918_412ea8438a_o.gif",
        "link_bin": "https://github.com/lmbstudiocontact/mb6_2/raw/main/GhibliAnime6_M6_2_Portuguese.bin",
        "name_language": "Portuguese",
        "id_bin_language": "GhibliAnime6_M6_2_Portuguese"
      },
      {
        "author": "LMB Studio",
        "link_thumb": "https://live.staticflickr.com/65535/51676817681_cc600df034_o.gif",
        "link_bin": "https://github.com/lmbstudiocontact/mb6_2/raw/main/GhibliAnime6_M6_2_Russian.bin",
        "name_language": "Russian",
        "id_bin_language": "GhibliAnime6_M6_2_Russian"
      },
      {
        "author": "LMB Studio",
        "link_thumb": "https://live.staticflickr.com/65535/51676817921_5eca8bedd2_o.gif",
        "link_bin": "https://github.com/lmbstudiocontact/mb6_2/raw/main/GhibliAnime6_M6_2_Spanish.bin",
        "name_language": "Spanish",
        "id_bin_language": "GhibliAnime6_M6_2_Spanish"
      }
    ],
    "array_tags": [
      "lmbstudio"
    ],
    "list_album": [
      {
        "id_album": "1193703152",
        "link_thumb": "https://live.staticflickr.com/65535/51676014262_a67fdcecfa_o.gif",
        "title": "Ghibli Anime_M6_2"
      }
    ]
  },
  {
    "author": "LMB Studio",
    "link_thumb": "https://live.staticflickr.com/65535/51677065503_a3f0df01a1_o.gif",
    "link_bin": "https://github.com/lmbstudiocontact/mb6_2/raw/main/GhibliAnime7_M6_2.bin",
    "id_bin": "GhibliAnime7_M6_2",
    "list_language": [
      {
        "author": "LMB Studio",
        "link_thumb": "https://live.staticflickr.com/65535/51677490664_9d50b257d3_o.gif",
        "link_bin": "https://github.com/lmbstudiocontact/mb6_2/raw/main/GhibliAnime7_M6_2_English.bin",
        "name_language": "English",
        "id_bin_language": "GhibliAnime7_M6_2_English"
      },
      {
        "author": "LMB Studio",
        "link_thumb": "https://live.staticflickr.com/65535/51677701335_d3f67b3944_o.gif",
        "link_bin": "https://github.com/lmbstudiocontact/mb6_2/raw/main/GhibliAnime7_M6_2_Portuguese.bin",
        "name_language": "Portuguese",
        "id_bin_language": "GhibliAnime7_M6_2_Portuguese"
      },
      {
        "author": "LMB Studio",
        "link_thumb": "https://live.staticflickr.com/65535/51676016332_17ba4e045e_o.gif",
        "link_bin": "https://github.com/lmbstudiocontact/mb6_2/raw/main/GhibliAnime7_M6_2_Russian.bin",
        "name_language": "Russian",
        "id_bin_language": "GhibliAnime7_M6_2_Russian"
      },
      {
        "author": "LMB Studio",
        "link_thumb": "https://live.staticflickr.com/65535/51677701935_3e49213344_o.gif",
        "link_bin": "https://github.com/lmbstudiocontact/mb6_2/raw/main/GhibliAnime7_M6_2_Spanish.bin",
        "name_language": "Spanish",
        "id_bin_language": "GhibliAnime7_M6_2_Spanish"
      }
    ],
    "array_tags": [
      "lmbstudio"
    ],
    "list_album": [
      {
        "id_album": "1193703152",
        "link_thumb": "https://live.staticflickr.com/65535/51677065503_a3f0df01a1_o.gif",
        "title": "Ghibli Anime_M6_2"
      }
    ]
  },
  {
    "author": "LMB Studio",
    "link_thumb": "https://live.staticflickr.com/65535/51677066973_267b26fa30_o.gif",
    "link_bin": "https://github.com/lmbstudiocontact/mb6_2/raw/main/GhibliAnime8_M6_2.bin",
    "id_bin": "GhibliAnime8_M6_2",
    "list_language": [
      {
        "author": "LMB Studio",
        "link_thumb": "https://live.staticflickr.com/65535/51676819921_d10d4d7cc3_o.gif",
        "link_bin": "https://github.com/lmbstudiocontact/mb6_2/raw/main/GhibliAnime8_M6_2_English.bin",
        "name_language": "English",
        "id_bin_language": "GhibliAnime8_M6_2_English"
      },
      {
        "author": "LMB Studio",
        "link_thumb": "https://live.staticflickr.com/65535/51677067393_5759deed4c_o.gif",
        "link_bin": "https://github.com/lmbstudiocontact/mb6_2/raw/main/GhibliAnime8_M6_2_Portuguese.bin",
        "name_language": "Portuguese",
        "id_bin_language": "GhibliAnime8_M6_2_Portuguese"
      },
      {
        "author": "LMB Studio",
        "link_thumb": "https://live.staticflickr.com/65535/51676017537_fd3df65846_o.gif",
        "link_bin": "https://github.com/lmbstudiocontact/mb6_2/raw/main/GhibliAnime8_M6_2_Russian.bin",
        "name_language": "Russian",
        "id_bin_language": "GhibliAnime8_M6_2_Russian"
      },
      {
        "author": "LMB Studio",
        "link_thumb": "https://live.staticflickr.com/65535/51676820691_a93abd3ea3_o.gif",
        "link_bin": "https://github.com/lmbstudiocontact/mb6_2/raw/main/GhibliAnime8_M6_2_Spanish.bin",
        "name_language": "Spanish",
        "id_bin_language": "GhibliAnime8_M6_2_Spanish"
      }
    ],
    "array_tags": [
      "lmbstudio"
    ],
    "list_album": [
      {
        "id_album": "1193703152",
        "link_thumb": "https://live.staticflickr.com/65535/51677066973_267b26fa30_o.gif",
        "title": "Ghibli Anime_M6_2"
      }
    ]
  },
  {
    "author": "LMB Studio",
    "link_thumb": "https://live.staticflickr.com/65535/51677703480_e1d6482355_o.gif",
    "link_bin": "https://github.com/lmbstudiocontact/mb6_2/raw/main/GhibliAnime9_M6_2.bin",
    "id_bin": "GhibliAnime9_M6_2",
    "list_language": [
      {
        "author": "LMB Studio",
        "link_thumb": "https://live.staticflickr.com/65535/51676018177_1240f143ae_o.gif",
        "link_bin": "https://github.com/lmbstudiocontact/mb6_2/raw/main/GhibliAnime9_M6_2_English.bin",
        "name_language": "English",
        "id_bin_language": "GhibliAnime9_M6_2_English"
      },
      {
        "author": "LMB Studio",
        "link_thumb": "https://live.staticflickr.com/65535/51677493519_960afc9951_o.gif",
        "link_bin": "https://github.com/lmbstudiocontact/mb6_2/raw/main/GhibliAnime9_M6_2_Portuguese.bin",
        "name_language": "Portuguese",
        "id_bin_language": "GhibliAnime9_M6_2_Portuguese"
      },
      {
        "author": "LMB Studio",
        "link_thumb": "https://live.staticflickr.com/65535/51676821661_eaa8963ebf_o.gif",
        "link_bin": "https://github.com/lmbstudiocontact/mb6_2/raw/main/GhibliAnime9_M6_2_Russian.bin",
        "name_language": "Russian",
        "id_bin_language": "GhibliAnime9_M6_2_Russian"
      },
      {
        "author": "LMB Studio",
        "link_thumb": "https://live.staticflickr.com/65535/51676018777_25667b304a_o.gif",
        "link_bin": "https://github.com/lmbstudiocontact/mb6_2/raw/main/GhibliAnime9_M6_2_Spanish.bin",
        "name_language": "Spanish",
        "id_bin_language": "GhibliAnime9_M6_2_Spanish"
      }
    ],
    "array_tags": [
      "lmbstudio"
    ],
    "list_album": [
      {
        "id_album": "1193703152",
        "link_thumb": "https://live.staticflickr.com/65535/51677703480_e1d6482355_o.gif",
        "title": "Ghibli Anime_M6_2"
      }
    ]
  }
]