[
  {
    "author": "neux",
    "link_thumb": "https://live.staticflickr.com/65535/51670214749_83fddcc550_o.gif",
    "link_bin": "https://github.com/lmbstudiocontact/mb6_0/raw/main/1589.bin",
    "id_bin": "1589",
    "list_language": [],
    "array_tags": [
      "black"
    ],
    "list_album": [
      {
        "id_album": "2433880",
        "link_thumb": "https://live.staticflickr.com/65535/51670214749_83fddcc550_o.gif",
        "title": "None"
      }
    ]
  },
  {
    "author": "blanchie_pie",
    "link_thumb": "https://live.staticflickr.com/65535/51670407475_3f1073c8bf_o.gif",
    "link_bin": "https://github.com/lmbstudiocontact/mb6_0/raw/main/1590.bin",
    "id_bin": "1590",
    "list_language": [],
    "array_tags": [
      "cat"
    ],
    "list_album": [
      {
        "id_album": "2433880",
        "link_thumb": "https://live.staticflickr.com/65535/51670407475_3f1073c8bf_o.gif",
        "title": "None"
      }
    ]
  },
  {
    "author": "blanchie_pie",
    "link_thumb": "https://live.staticflickr.com/65535/51668729892_b279c85f78_o.gif",
    "link_bin": "https://github.com/lmbstudiocontact/mb6_0/raw/main/1596.bin",
    "id_bin": "1596",
    "list_language": [],
    "array_tags": [
      "cat"
    ],
    "list_album": [
      {
        "id_album": "2433880",
        "link_thumb": "https://live.staticflickr.com/65535/51668729892_b279c85f78_o.gif",
        "title": "None"
      }
    ]
  },
  {
    "author": "mtaras",
    "link_thumb": "https://live.staticflickr.com/65535/51669768798_fa9ee6abbe_o.gif",
    "link_bin": "https://github.com/lmbstudiocontact/mb6_0/raw/main/1598.bin",
    "id_bin": "1598",
    "list_language": [],
    "array_tags": [
      "digital",
      "date",
      "distance",
      "heartrate",
      "weather",
      "battery",
      "steps"
    ],
    "list_album": [
      {
        "id_album": "2433880",
        "link_thumb": "https://live.staticflickr.com/65535/51669768798_fa9ee6abbe_o.gif",
        "title": "None"
      }
    ]
  },
  {
    "author": "blanchie_pie",
    "link_thumb": "https://live.staticflickr.com/65535/51669528091_6da8062d48_o.gif",
    "link_bin": "https://github.com/lmbstudiocontact/mb6_0/raw/main/1599.bin",
    "id_bin": "1599",
    "list_language": [],
    "array_tags": [
      "black"
    ],
    "list_album": [
      {
        "id_album": "2433880",
        "link_thumb": "https://live.staticflickr.com/65535/51669528091_6da8062d48_o.gif",
        "title": "None"
      }
    ]
  },
  {
    "author": "neux",
    "link_thumb": "https://live.staticflickr.com/65535/51670408515_ce4884676d_o.gif",
    "link_bin": "https://github.com/lmbstudiocontact/mb6_0/raw/main/1601.bin",
    "id_bin": "1601",
    "list_language": [],
    "array_tags": [
      "black",
      "simple"
    ],
    "list_album": [
      {
        "id_album": "2433880",
        "link_thumb": "https://live.staticflickr.com/65535/51670408515_ce4884676d_o.gif",
        "title": "None"
      }
    ]
  },
  {
    "author": "neux",
    "link_thumb": "https://live.staticflickr.com/65535/51670216339_c8b6a53e39_o.gif",
    "link_bin": "https://github.com/lmbstudiocontact/mb6_0/raw/main/1602.bin",
    "id_bin": "1602",
    "list_language": [],
    "array_tags": [
      "simple"
    ],
    "list_album": [
      {
        "id_album": "2433880",
        "link_thumb": "https://live.staticflickr.com/65535/51670216339_c8b6a53e39_o.gif",
        "title": "None"
      }
    ]
  },
  {
    "author": "neux",
    "link_thumb": "https://live.staticflickr.com/65535/51669769978_bfed13aa7c_o.gif",
    "link_bin": "https://github.com/lmbstudiocontact/mb6_0/raw/main/1603.bin",
    "id_bin": "1603",
    "list_language": [],
    "array_tags": [
      "date",
      "pulse",
      "time",
      "battery",
      "steps"
    ],
    "list_album": [
      {
        "id_album": "2433880",
        "link_thumb": "https://live.staticflickr.com/65535/51669769978_bfed13aa7c_o.gif",
        "title": "None"
      }
    ]
  },
  {
    "author": "sachok",
    "link_thumb": "https://live.staticflickr.com/65535/51669770093_9a82444e2c_o.gif",
    "link_bin": "https://github.com/lmbstudiocontact/mb6_0/raw/main/1604.bin",
    "id_bin": "1604",
    "list_language": [],
    "array_tags": [
      "digital",
      "date",
      "heartrate",
      "weekday",
      "calories",
      "battery",
      "steps",
      "donotdisturb",
      "seconds",
      "bluetooth",
      "weather",
      "alarm",
      "lock"
    ],
    "list_album": [
      {
        "id_album": "2433880",
        "link_thumb": "https://live.staticflickr.com/65535/51669770093_9a82444e2c_o.gif",
        "title": "None"
      }
    ]
  },
  {
    "author": "neux",
    "link_thumb": "https://live.staticflickr.com/65535/51669529466_e7772a8e1b_o.gif",
    "link_bin": "https://github.com/lmbstudiocontact/mb6_0/raw/main/1605.bin",
    "id_bin": "1605",
    "list_language": [],
    "array_tags": [
      "date",
      "black",
      "weather",
      "battery",
      "sport",
      "steps"
    ],
    "list_album": [
      {
        "id_album": "2433880",
        "link_thumb": "https://live.staticflickr.com/65535/51669529466_e7772a8e1b_o.gif",
        "title": "None"
      }
    ]
  },
  {
    "author": "neux",
    "link_thumb": "https://live.staticflickr.com/65535/51670409290_c51e1d400a_o.gif",
    "link_bin": "https://github.com/lmbstudiocontact/mb6_0/raw/main/1606.bin",
    "id_bin": "1606",
    "list_language": [],
    "array_tags": [
      "simple",
      "time"
    ],
    "list_album": [
      {
        "id_album": "2433880",
        "link_thumb": "https://live.staticflickr.com/65535/51670409290_c51e1d400a_o.gif",
        "title": "None"
      }
    ]
  },
  {
    "author": "neux",
    "link_thumb": "https://live.staticflickr.com/65535/51668731747_4e5a24f108_o.gif",
    "link_bin": "https://github.com/lmbstudiocontact/mb6_0/raw/main/1607.bin",
    "id_bin": "1607",
    "list_language": [],
    "array_tags": [
      "black",
      "time"
    ],
    "list_album": [
      {
        "id_album": "2433880",
        "link_thumb": "https://live.staticflickr.com/65535/51668731747_4e5a24f108_o.gif",
        "title": "None"
      }
    ]
  },
  {
    "author": "neux",
    "link_thumb": "https://live.staticflickr.com/65535/51669770668_1cd9d497af_o.gif",
    "link_bin": "https://github.com/lmbstudiocontact/mb6_0/raw/main/1608.bin",
    "id_bin": "1608",
    "list_language": [],
    "array_tags": [
      "date",
      "pulse",
      "animated",
      "time",
      "steps"
    ],
    "list_album": [
      {
        "id_album": "2433880",
        "link_thumb": "https://live.staticflickr.com/65535/51669770668_1cd9d497af_o.gif",
        "title": "None"
      }
    ]
  },
  {
    "author": "TsReal30",
    "link_thumb": "https://live.staticflickr.com/65535/51669770858_6c760b4949_o.gif",
    "link_bin": "https://github.com/lmbstudiocontact/mb6_0/raw/main/161.bin",
    "id_bin": "161",
    "list_language": [],
    "array_tags": [
      "apple"
    ],
    "list_album": [
      {
        "id_album": "2433880",
        "link_thumb": "https://live.staticflickr.com/65535/51669770858_6c760b4949_o.gif",
        "title": "None"
      }
    ]
  },
  {
    "author": "Riqos",
    "link_thumb": "https://live.staticflickr.com/65535/51669530216_36fabb9c83_o.gif",
    "link_bin": "https://github.com/lmbstudiocontact/mb6_0/raw/main/1611.bin",
    "id_bin": "1611",
    "list_language": [],
    "array_tags": [
      "digital",
      "date",
      "heartrate",
      "weekday",
      "battery",
      "steps"
    ],
    "list_album": [
      {
        "id_album": "2433880",
        "link_thumb": "https://live.staticflickr.com/65535/51669530216_36fabb9c83_o.gif",
        "title": "None"
      }
    ]
  },
  {
    "author": "cbpopeye",
    "link_thumb": "https://live.staticflickr.com/65535/51670217714_0d0c1545f6_o.gif",
    "link_bin": "https://github.com/lmbstudiocontact/mb6_0/raw/main/1613.bin",
    "id_bin": "1613",
    "list_language": [],
    "array_tags": [
      "clock"
    ],
    "list_album": [
      {
        "id_album": "2433880",
        "link_thumb": "https://live.staticflickr.com/65535/51670217714_0d0c1545f6_o.gif",
        "title": "None"
      }
    ]
  },
  {
    "author": "neux",
    "link_thumb": "https://live.staticflickr.com/65535/51669771403_8829696b0b_o.gif",
    "link_bin": "https://github.com/lmbstudiocontact/mb6_0/raw/main/1614.bin",
    "id_bin": "1614",
    "list_language": [],
    "array_tags": [
      "date",
      "soccer",
      "time",
      "sport"
    ],
    "list_album": [
      {
        "id_album": "2433880",
        "link_thumb": "https://live.staticflickr.com/65535/51669771403_8829696b0b_o.gif",
        "title": "None"
      }
    ]
  },
  {
    "author": "molodez_tom",
    "link_thumb": "https://live.staticflickr.com/65535/51669530731_92cfbb1a48_o.gif",
    "link_bin": "https://github.com/lmbstudiocontact/mb6_0/raw/main/1616.bin",
    "id_bin": "1616",
    "list_language": [],
    "array_tags": [
      "weather",
      "alarm",
      "pai",
      "calories"
    ],
    "list_album": [
      {
        "id_album": "2433880",
        "link_thumb": "https://live.staticflickr.com/65535/51669530731_92cfbb1a48_o.gif",
        "title": "None"
      }
    ]
  },
  {
    "author": "neux",
    "link_thumb": "https://live.staticflickr.com/65535/51669771798_a6e83b0cc4_o.gif",
    "link_bin": "https://github.com/lmbstudiocontact/mb6_0/raw/main/1618.bin",
    "id_bin": "1618",
    "list_language": [],
    "array_tags": [
      "soccer",
      "time",
      "sport"
    ],
    "list_album": [
      {
        "id_album": "2433880",
        "link_thumb": "https://live.staticflickr.com/65535/51669771798_a6e83b0cc4_o.gif",
        "title": "None"
      }
    ]
  },
  {
    "author": "neux",
    "link_thumb": "https://live.staticflickr.com/65535/51670410895_fc079b6d1c_o.gif",
    "link_bin": "https://github.com/lmbstudiocontact/mb6_0/raw/main/1621.bin",
    "id_bin": "1621",
    "list_language": [],
    "array_tags": [
      "soccer",
      "time",
      "sport"
    ],
    "list_album": [
      {
        "id_album": "2433880",
        "link_thumb": "https://live.staticflickr.com/65535/51670410895_fc079b6d1c_o.gif",
        "title": "None"
      }
    ]
  },
  {
    "author": "SanKarstiko",
    "link_thumb": "https://live.staticflickr.com/65535/51670218644_0d7cc5fe24_o.gif",
    "link_bin": "https://github.com/lmbstudiocontact/mb6_0/raw/main/1622.bin",
    "id_bin": "1622",
    "list_language": [],
    "array_tags": [
      "digital",
      "date",
      "heartrate",
      "calories",
      "battery",
      "steps"
    ],
    "list_album": [
      {
        "id_album": "2433880",
        "link_thumb": "https://live.staticflickr.com/65535/51670218644_0d7cc5fe24_o.gif",
        "title": "None"
      }
    ]
  },
  {
    "author": "Вепрь",
    "link_thumb": "https://live.staticflickr.com/65535/51670411275_ef700f9a98_o.gif",
    "link_bin": "https://github.com/lmbstudiocontact/mb6_0/raw/main/1624.bin",
    "id_bin": "1624",
    "list_language": [],
    "array_tags": [
      "digital",
      "date",
      "distance",
      "heartrate",
      "weather",
      "battery",
      "steps"
    ],
    "list_album": [
      {
        "id_album": "2433880",
        "link_thumb": "https://live.staticflickr.com/65535/51670411275_ef700f9a98_o.gif",
        "title": "None"
      }
    ]
  },
  {
    "author": "Вепрь",
    "link_thumb": "https://live.staticflickr.com/65535/51668733647_5fd15e1315_o.gif",
    "link_bin": "https://github.com/lmbstudiocontact/mb6_0/raw/main/1625.bin",
    "id_bin": "1625",
    "list_language": [],
    "array_tags": [
      "digital",
      "date",
      "distance",
      "heartrate",
      "weather",
      "battery",
      "steps"
    ],
    "list_album": [
      {
        "id_album": "2433880",
        "link_thumb": "https://live.staticflickr.com/65535/51668733647_5fd15e1315_o.gif",
        "title": "None"
      }
    ]
  },
  {
    "author": "Nikwnasv",
    "link_thumb": "https://live.staticflickr.com/65535/51669772723_0f5c28268f_o.gif",
    "link_bin": "https://github.com/lmbstudiocontact/mb6_0/raw/main/1626.bin",
    "id_bin": "1626",
    "list_language": [],
    "array_tags": [
      "red",
      "date",
      "bluetooth",
      "games",
      "dnd",
      "battery"
    ],
    "list_album": [
      {
        "id_album": "2433880",
        "link_thumb": "https://live.staticflickr.com/65535/51669772723_0f5c28268f_o.gif",
        "title": "None"
      }
    ]
  },
  {
    "author": "None",
    "link_thumb": "https://live.staticflickr.com/65535/51669772893_dccf887972_o.gif",
    "link_bin": "https://github.com/lmbstudiocontact/mb6_0/raw/main/1629.bin",
    "id_bin": "1629",
    "list_language": [],
    "array_tags": [],
    "list_album": [
      {
        "id_album": "2433880",
        "link_thumb": "https://live.staticflickr.com/65535/51669772893_dccf887972_o.gif",
        "title": "None"
      }
    ]
  },
  {
    "author": "jase724",
    "link_thumb": "https://live.staticflickr.com/65535/51670412280_bbdc622a57_o.gif",
    "link_bin": "https://github.com/lmbstudiocontact/mb6_0/raw/main/1632.bin",
    "id_bin": "1632",
    "list_language": [],
    "array_tags": [
      "date",
      "digital",
      "analog",
      "heartrate",
      "calories",
      "battery",
      "steps"
    ],
    "list_album": [
      {
        "id_album": "2433880",
        "link_thumb": "https://live.staticflickr.com/65535/51670412280_bbdc622a57_o.gif",
        "title": "None"
      }
    ]
  },
  {
    "author": "yupoooo",
    "link_thumb": "https://live.staticflickr.com/65535/51669532781_b2db2a04b3_o.gif",
    "link_bin": "https://github.com/lmbstudiocontact/mb6_0/raw/main/1634.bin",
    "id_bin": "1634",
    "list_language": [],
    "array_tags": [],
    "list_album": [
      {
        "id_album": "2433880",
        "link_thumb": "https://live.staticflickr.com/65535/51669532781_b2db2a04b3_o.gif",
        "title": "None"
      }
    ]
  },
  {
    "author": "kutuzov",
    "link_thumb": "https://live.staticflickr.com/65535/51670220284_c56f4cd006_o.gif",
    "link_bin": "https://github.com/lmbstudiocontact/mb6_0/raw/main/1635.bin",
    "id_bin": "1635",
    "list_language": [],
    "array_tags": [
      "date",
      "digital",
      "battery"
    ],
    "list_album": [
      {
        "id_album": "2433880",
        "link_thumb": "https://live.staticflickr.com/65535/51670220284_c56f4cd006_o.gif",
        "title": "None"
      }
    ]
  },
  {
    "author": "GrimReaperCZ",
    "link_thumb": "https://live.staticflickr.com/65535/51669774018_6c9d28758a_o.gif",
    "link_bin": "https://github.com/lmbstudiocontact/mb6_0/raw/main/1637.bin",
    "id_bin": "1637",
    "list_language": [],
    "array_tags": [
      "digital",
      "date",
      "game",
      "heartrate",
      "games",
      "battery",
      "steps"
    ],
    "list_album": [
      {
        "id_album": "2433880",
        "link_thumb": "https://live.staticflickr.com/65535/51669774018_6c9d28758a_o.gif",
        "title": "None"
      }
    ]
  },
  {
    "author": "Tiansinichi17",
    "link_thumb": "https://live.staticflickr.com/65535/51668735362_b5c33b833e_o.gif",
    "link_bin": "https://github.com/lmbstudiocontact/mb6_0/raw/main/1640.bin",
    "id_bin": "1640",
    "list_language": [],
    "array_tags": [],
    "list_album": [
      {
        "id_album": "2433880",
        "link_thumb": "https://live.staticflickr.com/65535/51668735362_b5c33b833e_o.gif",
        "title": "None"
      }
    ]
  },
  {
    "author": "shymik",
    "link_thumb": "https://live.staticflickr.com/65535/51670413465_d6f113ee7a_o.gif",
    "link_bin": "https://github.com/lmbstudiocontact/mb6_0/raw/main/1641.bin",
    "id_bin": "1641",
    "list_language": [],
    "array_tags": [
      "digital",
      "date",
      "distance",
      "heartrate",
      "calories",
      "battery",
      "steps"
    ],
    "list_album": [
      {
        "id_album": "2433880",
        "link_thumb": "https://live.staticflickr.com/65535/51670413465_d6f113ee7a_o.gif",
        "title": "None"
      }
    ]
  },
  {
    "author": "ryundel",
    "link_thumb": "https://live.staticflickr.com/65535/51670221309_5fdcfee127_o.gif",
    "link_bin": "https://github.com/lmbstudiocontact/mb6_0/raw/main/1642.bin",
    "id_bin": "1642",
    "list_language": [],
    "array_tags": [
      "digital"
    ],
    "list_album": [
      {
        "id_album": "2433880",
        "link_thumb": "https://live.staticflickr.com/65535/51670221309_5fdcfee127_o.gif",
        "title": "None"
      }
    ]
  },
  {
    "author": "adityappi",
    "link_thumb": "https://live.staticflickr.com/65535/51670414145_b95dd62928_o.gif",
    "link_bin": "https://github.com/lmbstudiocontact/mb6_0/raw/main/1645.bin",
    "id_bin": "1645",
    "list_language": [],
    "array_tags": [
      "red",
      "date",
      "white",
      "pulse",
      "simple",
      "battery",
      "day",
      "steps"
    ],
    "list_album": [
      {
        "id_album": "2433880",
        "link_thumb": "https://live.staticflickr.com/65535/51670414145_b95dd62928_o.gif",
        "title": "None"
      }
    ]
  },
  {
    "author": "SamRK",
    "link_thumb": "https://live.staticflickr.com/65535/51670414355_b6e3c1735e_o.gif",
    "link_bin": "https://github.com/lmbstudiocontact/mb6_0/raw/main/1646.bin",
    "id_bin": "1646",
    "list_language": [],
    "array_tags": [
      "date",
      "bluetooth",
      "pulse",
      "time",
      "battery",
      "steps"
    ],
    "list_album": [
      {
        "id_album": "2433880",
        "link_thumb": "https://live.staticflickr.com/65535/51670414355_b6e3c1735e_o.gif",
        "title": "None"
      }
    ]
  },
  {
    "author": "SanKarstiko",
    "link_thumb": "https://live.staticflickr.com/65535/51670414480_7a0bc254cc_o.gif",
    "link_bin": "https://github.com/lmbstudiocontact/mb6_0/raw/main/1648.bin",
    "id_bin": "1648",
    "list_language": [],
    "array_tags": [
      "digital",
      "date",
      "distance",
      "heartrate",
      "calories",
      "battery",
      "steps"
    ],
    "list_album": [
      {
        "id_album": "2433880",
        "link_thumb": "https://live.staticflickr.com/65535/51670414480_7a0bc254cc_o.gif",
        "title": "None"
      }
    ]
  },
  {
    "author": "shymik",
    "link_thumb": "https://live.staticflickr.com/65535/51669776103_102782fb03_o.gif",
    "link_bin": "https://github.com/lmbstudiocontact/mb6_0/raw/main/1652.bin",
    "id_bin": "1652",
    "list_language": [],
    "array_tags": [
      "digital",
      "date",
      "seconds",
      "weather",
      "battery",
      "steps"
    ],
    "list_album": [
      {
        "id_album": "2433880",
        "link_thumb": "https://live.staticflickr.com/65535/51669776103_102782fb03_o.gif",
        "title": "None"
      }
    ]
  },
  {
    "author": "Nikwnasv",
    "link_thumb": "https://live.staticflickr.com/65535/51670415175_d2c9cf8376_o.gif",
    "link_bin": "https://github.com/lmbstudiocontact/mb6_0/raw/main/1658.bin",
    "id_bin": "1658",
    "list_language": [],
    "array_tags": [
      "digital",
      "date",
      "bluetooth",
      "heartrate",
      "pulse",
      "animated",
      "battery",
      "steps",
      "status",
      "animation"
    ],
    "list_album": [
      {
        "id_album": "2433880",
        "link_thumb": "https://live.staticflickr.com/65535/51670415175_d2c9cf8376_o.gif",
        "title": "None"
      }
    ]
  },
  {
    "author": "Rosta949",
    "link_thumb": "https://live.staticflickr.com/65535/51669776628_9e0f7d978f_o.gif",
    "link_bin": "https://github.com/lmbstudiocontact/mb6_0/raw/main/1659.bin",
    "id_bin": "1659",
    "list_language": [],
    "array_tags": [
      "digital",
      "date",
      "weather",
      "weekday",
      "alarm",
      "pulse",
      "calories",
      "battery",
      "status",
      "animation"
    ],
    "list_album": [
      {
        "id_album": "2433880",
        "link_thumb": "https://live.staticflickr.com/65535/51669776628_9e0f7d978f_o.gif",
        "title": "None"
      }
    ]
  },
  {
    "author": "TsReal30",
    "link_thumb": "https://live.staticflickr.com/65535/51669535851_abd1b43f49_o.gif",
    "link_bin": "https://github.com/lmbstudiocontact/mb6_0/raw/main/166.bin",
    "id_bin": "166",
    "list_language": [],
    "array_tags": [
      "white"
    ],
    "list_album": [
      {
        "id_album": "2433880",
        "link_thumb": "https://live.staticflickr.com/65535/51669535851_abd1b43f49_o.gif",
        "title": "None"
      }
    ]
  },
  {
    "author": "blanchie_pie",
    "link_thumb": "https://live.staticflickr.com/65535/51669536656_605273170a_o.gif",
    "link_bin": "https://github.com/lmbstudiocontact/mb6_0/raw/main/1663.bin",
    "id_bin": "1663",
    "list_language": [],
    "array_tags": [
      "digital",
      "date",
      "heartrate",
      "weather",
      "calories",
      "battery",
      "steps"
    ],
    "list_album": [
      {
        "id_album": "2433880",
        "link_thumb": "https://live.staticflickr.com/65535/51669536656_605273170a_o.gif",
        "title": "None"
      }
    ]
  },
  {
    "author": ".Kosmik",
    "link_thumb": "https://live.staticflickr.com/65535/51669777733_56c94bf246_o.gif",
    "link_bin": "https://github.com/lmbstudiocontact/mb6_0/raw/main/1664.bin",
    "id_bin": "1664",
    "list_language": [],
    "array_tags": [
      "digital",
      "date",
      "battery",
      "steps"
    ],
    "list_album": [
      {
        "id_album": "2433880",
        "link_thumb": "https://live.staticflickr.com/65535/51669777733_56c94bf246_o.gif",
        "title": "None"
      }
    ]
  },
  {
    "author": "Riqos",
    "link_thumb": "https://live.staticflickr.com/65535/51668738842_68dddd8950_o.gif",
    "link_bin": "https://github.com/lmbstudiocontact/mb6_0/raw/main/1668.bin",
    "id_bin": "1668",
    "list_language": [],
    "array_tags": [
      "digital",
      "date",
      "month",
      "heartrate",
      "weekday",
      "time",
      "battery",
      "steps"
    ],
    "list_album": [
      {
        "id_album": "2433880",
        "link_thumb": "https://live.staticflickr.com/65535/51668738842_68dddd8950_o.gif",
        "title": "None"
      }
    ]
  },
  {
    "author": "Rosta949",
    "link_thumb": "https://live.staticflickr.com/65535/51669537286_7191d76129_o.gif",
    "link_bin": "https://github.com/lmbstudiocontact/mb6_1/raw/main/1669.bin",
    "id_bin": "1669",
    "list_language": [],
    "array_tags": [
      "date",
      "weekday",
      "weather",
      "battery",
      "animation"
    ],
    "list_album": [
      {
        "id_album": "2433880",
        "link_thumb": "https://live.staticflickr.com/65535/51669537286_7191d76129_o.gif",
        "title": "None"
      }
    ]
  },
  {
    "author": "TsReal30",
    "link_thumb": "https://live.staticflickr.com/65535/51669778398_56b23a910e_o.gif",
    "link_bin": "https://github.com/lmbstudiocontact/mb6_0/raw/main/167.bin",
    "id_bin": "167",
    "list_language": [],
    "array_tags": [],
    "list_album": [
      {
        "id_album": "2433880",
        "link_thumb": "https://live.staticflickr.com/65535/51669778398_56b23a910e_o.gif",
        "title": "None"
      }
    ]
  },
  {
    "author": "uapa",
    "link_thumb": "https://live.staticflickr.com/65535/51670417500_44cb66bcb9_o.gif",
    "link_bin": "https://github.com/lmbstudiocontact/mb6_1/raw/main/1673.bin",
    "id_bin": "1673",
    "list_language": [],
    "array_tags": [
      "digital",
      "distance",
      "weekday",
      "pulse",
      "calories",
      "battery",
      "steps"
    ],
    "list_album": [
      {
        "id_album": "2433880",
        "link_thumb": "https://live.staticflickr.com/65535/51670417500_44cb66bcb9_o.gif",
        "title": "None"
      }
    ]
  },
  {
    "author": "mediatouch",
    "link_thumb": "https://live.staticflickr.com/65535/51669537866_ce975639d7_o.gif",
    "link_bin": "https://github.com/lmbstudiocontact/mb6_1/raw/main/1674.bin",
    "id_bin": "1674",
    "list_language": [],
    "array_tags": [
      "digital",
      "date",
      "distance",
      "heartrate",
      "calories",
      "battery",
      "steps",
      "month",
      "weather",
      "temperature",
      "pulse",
      "day",
      "status"
    ],
    "list_album": [
      {
        "id_album": "2433880",
        "link_thumb": "https://live.staticflickr.com/65535/51669537866_ce975639d7_o.gif",
        "title": "None"
      }
    ]
  },
  {
    "author": "buraklarca",
    "link_thumb": "https://live.staticflickr.com/65535/51669779303_bef55ba3e2_o.gif",
    "link_bin": "https://github.com/lmbstudiocontact/mb6_0/raw/main/168.bin",
    "id_bin": "168",
    "list_language": [],
    "array_tags": [
      "digital",
      "date",
      "seconds",
      "heartrate",
      "weather",
      "battery",
      "steps"
    ],
    "list_album": [
      {
        "id_album": "2433880",
        "link_thumb": "https://live.staticflickr.com/65535/51669779303_bef55ba3e2_o.gif",
        "title": "None"
      }
    ]
  },
  {
    "author": "Rosta949",
    "link_thumb": "https://live.staticflickr.com/65535/51669779448_2dea77e1d4_o.gif",
    "link_bin": "https://github.com/lmbstudiocontact/mb6_1/raw/main/1686.bin",
    "id_bin": "1686",
    "list_language": [],
    "array_tags": [
      "digital",
      "date",
      "weekday",
      "battery"
    ],
    "list_album": [
      {
        "id_album": "2433880",
        "link_thumb": "https://live.staticflickr.com/65535/51669779448_2dea77e1d4_o.gif",
        "title": "None"
      }
    ]
  },
  {
    "author": "Rosta949",
    "link_thumb": "https://live.staticflickr.com/65535/51669779623_467173053f_o.gif",
    "link_bin": "https://github.com/lmbstudiocontact/mb6_1/raw/main/1687.bin",
    "id_bin": "1687",
    "list_language": [],
    "array_tags": [
      "digital",
      "date",
      "weather",
      "weekday",
      "battery"
    ],
    "list_album": [
      {
        "id_album": "2433880",
        "link_thumb": "https://live.staticflickr.com/65535/51669779623_467173053f_o.gif",
        "title": "None"
      }
    ]
  },
  {
    "author": "tecladaise",
    "link_thumb": "https://live.staticflickr.com/65535/51668740442_84d4901b5c_o.gif",
    "link_bin": "https://github.com/lmbstudiocontact/mb6_1/raw/main/1689.bin",
    "id_bin": "1689",
    "list_language": [],
    "array_tags": [
      "bluetooth",
      "weather",
      "battery",
      "steps"
    ],
    "list_album": [
      {
        "id_album": "2433880",
        "link_thumb": "https://live.staticflickr.com/65535/51668740442_84d4901b5c_o.gif",
        "title": "None"
      }
    ]
  }
]